pygismeteo/__init__.py
pygismeteo/_gismeteo.py
pygismeteo/_http.py
pygismeteo/py.typed
pygismeteo/types.py
pygismeteo/_endpoints/__init__.py
pygismeteo/_endpoints/current.py
pygismeteo/_endpoints/search.py
pygismeteo/_endpoints/step24.py
pygismeteo/_endpoints/step3.py
pygismeteo/_endpoints/step6.py
pygismeteo-8.0.1.dist-info/METADATA
pygismeteo-8.0.1.dist-info/WHEEL
pygismeteo-8.0.1.dist-info/licenses/LICENSE
pygismeteo-8.0.1.dist-info/RECORD
